bookbuilderpy/__init__.py
bookbuilderpy/build.py
bookbuilderpy/build_result.py
bookbuilderpy/compress.py
bookbuilderpy/constants.py
bookbuilderpy/format_python.py
bookbuilderpy/git.py
bookbuilderpy/html.py
bookbuilderpy/logger.py
bookbuilderpy/pandoc.py
bookbuilderpy/parse_metadata.py
bookbuilderpy/path.py
bookbuilderpy/pdf.py
bookbuilderpy/preprocessor.py
bookbuilderpy/preprocessor_code.py
bookbuilderpy/preprocessor_commands.py
bookbuilderpy/preprocessor_input.py
bookbuilderpy/shell.py
bookbuilderpy/source_tools.py
bookbuilderpy/strings.py
bookbuilderpy/temp.py
bookbuilderpy/types.py
bookbuilderpy/url.py
bookbuilderpy/version.py
bookbuilderpy/versions.py
bookbuilderpy/website.py
bookbuilderpy/resources/GitHub.html5
bookbuilderpy/resources/GitHub.html5_license
bookbuilderpy/resources/__init__.py
bookbuilderpy/resources/_generate_resources.py
bookbuilderpy/resources/_resource.py
bookbuilderpy/resources/_resource_server.py
bookbuilderpy/resources/association-for-computing-machinery.csl
bookbuilderpy/resources/eisvogel.tex
bookbuilderpy/resources/eisvogel.tex_license
bookbuilderpy/resources/mathjax.js
bookbuilderpy/resources/mathjax.js_license
bookbuilderpy-1.9.27.dist-info/METADATA
bookbuilderpy-1.9.27.dist-info/WHEEL
bookbuilderpy-1.9.27.dist-info/top_level.txt
bookbuilderpy-1.9.27.dist-info/RECORD
