Metadata-Version: 2.1
Name: bookbuilderpy
Version: 1.9.27
Summary: A package for compiling electronic books.
Home-page: https://thomasweise.github.io/bookbuilderpy
Author: Thomas Weise
Author-email: tweise@ustc.edu.cn
Maintainer: Thomas Weise
Maintainer-email: tweise@ustc.edu.cn
License: GPL 3.0
Project-URL: Documentation, https://thomasweise.github.io/bookbuilderpy
Project-URL: Source, https://github.com/thomasWeise/bookbuilderpy/
Project-URL: Tracker, https://github.com/thomasWeise/bookbuilderpy/issues
Keywords: electronic books,books,markdown,html,pdf,epub,azw3,pandoc
Classifier: Development Status :: 4 - Beta
Classifier: Intended Audience :: Education
Classifier: License :: OSI Approved :: GNU General Public License v3 (GPLv3)
Classifier: Programming Language :: Python :: 3 :: Only
Classifier: Programming Language :: Python :: 3.9
Classifier: Programming Language :: Python :: 3.10
Classifier: Operating System :: POSIX :: Linux
Requires-Python: >=3.9
Requires-Dist: beautifulsoup4 (>=4.11.1)
Requires-Dist: markdown (>=3.4.1)
Requires-Dist: minify-html (>=0.9.2)
Requires-Dist: pyyaml (>=6.0)
Requires-Dist: regex (>=2022.07.09)
Requires-Dist: selenium (>=4.3.0)
Requires-Dist: strip-hints (>=0.1.10)
Requires-Dist: urllib3 (>=1.26.10)
Requires-Dist: yapf (>=0.32.0)
